{
    "IsEncrypted": false,
    "Values": {
        "AzureWebJobsStorage": "UseDevelopmentStorage=true",
        "FUNCTIONS_WORKER_RUNTIME": "dotnet-isolated"
    },
    "ConnectionStrings": {
        "RtsDB": ""
    },
    "AppSettings": {
        "AzureAppConfiguration": {
            "Endpoint": "",
            "IdentityClientID": ""
        },
        "AzureVaultUri": "",
        "RtsApiBaseUrl": "",
        "RtsApiClientId": "",
        "RtsApiClientSecret": "",
        "RtsAuthApiBaseUrl": ""
    }
}